pylrclibup/__init__.py
pylrclibup/config.py
pylrclibup/exceptions.py
pylrclibup/i18n.py
pylrclibup/logging_utils.py
pylrclibup/py.typed
pylrclibup/api/__init__.py
pylrclibup/api/client.py
pylrclibup/api/http.py
pylrclibup/api/pow.py
pylrclibup/api/publish.py
pylrclibup/cli/__init__.py
pylrclibup/cli/main.py
pylrclibup/fs/__init__.py
pylrclibup/fs/cleaner.py
pylrclibup/fs/mover.py
pylrclibup/lrc/__init__.py
pylrclibup/lrc/matcher.py
pylrclibup/lrc/parser.py
pylrclibup/model/__init__.py
pylrclibup/model/lyrics.py
pylrclibup/model/track.py
pylrclibup/processor/__init__.py
pylrclibup/processor/core.py
pylrclibup-0.5.4.dist-info/licenses/LICENSE
pylrclibup-0.5.4.dist-info/METADATA
pylrclibup-0.5.4.dist-info/WHEEL
pylrclibup-0.5.4.dist-info/entry_points.txt
pylrclibup-0.5.4.dist-info/top_level.txt
pylrclibup-0.5.4.dist-info/RECORD
