Metadata-Version: 2.4
Name: pylrclibup
Version: 0.5.4
Summary: A robust Python CLI tool for uploading lyrics or instrumental tags to LRCLIB.
Author-email: Harmonese <soundwaveradiator@gmail.com>
License-Expression: MIT
Project-URL: Homepage, https://github.com/Harmonese/pylrclibup
Project-URL: Source, https://github.com/Harmonese/pylrclibup
Project-URL: Issues, https://github.com/Harmonese/pylrclibup/issues
Keywords: lrclib,lyrics,lrc,music,metadata
Requires-Python: >=3.10
License-File: LICENSE
Requires-Dist: requests>=2.31.0
Requires-Dist: mutagen>=1.47
Requires-Dist: babel>=2.12.0
Requires-Dist: pyyaml>=6.0
Dynamic: license-file
